[
    {
        "state": "WEST BENGAL",
        "district": "",
        "police_station": "",
        "fir_number": "",
        "fir_date": "",
        "case_no": "Behala PS/115/12",
        "under_section": "379 IPC",
        "vehicle_registration_no": "WB25E1890",
        "vehicle_type": "",
        "status": "Stolen",
        "control_room_no.": "",
        "complainant": "",
        "complainant_address": "",
        "vehicle_engine_no.": "D27052815",
        "vehicle_chasis_no.": "MC1D4DHA3CP018249",
        "vehicle_make": "",
        "vehicle_color": "Silver",
        "vehicle_model": "",
        "stolen_from": "Opposite Mahananda Hospital on Jems Long Sarani",
        "stolen_date": "18/03/2012",
        "Select_Vehicle": "",
        "Select_Status": "M",
        "Trace_Address": "",
        "Date_Of_Trace": "",
        "Presently_At": "",
        "Display": ""
    },
    {
        "state": "WEST BENGAL",
        "district": "",
        "police_station": "",
        "fir_number": "",
        "fir_date": "",
        "case_no": "Regent Park PS/58/12",
        "under_section": "379 IPC",
        "vehicle_registration_no": "WB24Q9595",
        "vehicle_type": "Samurai",
        "status": "Stolen",
        "control_room_no.": "",
        "complainant": "",
        "complainant_address": "",
        "vehicle_engine_no.": "DHGBTC52806",
        "vehicle_chasis_no.": "MD2DHDHZZTCC63466",
        "vehicle_make": "Suzuki",
        "vehicle_color": "Black",
        "vehicle_model": "Samurai",
        "stolen_from": "65 Balaram Ghosh Road Kol 40",
        "stolen_date": "14/03/2012",
        "Select_Vehicle": "",
        "Select_Status": "M",
        "Trace_Address": "",
        "Date_Of_Trace": "",
        "Presently_At": "",
        "Display": ""
    },
    {
        "state": "WEST BENGAL",
        "district": "",
        "police_station": "",
        "fir_number": "",
        "fir_date": "",
        "case_no": "Behala PS/108/12",
        "under_section": "379 IPC",
        "vehicle_registration_no": "WB20M9053",
        "vehicle_type": "",
        "status": "Stolen",
        "control_room_no.": "",
        "complainant": "",
        "complainant_address": "",
        "vehicle_engine_no.": "DSGBMC04824",
        "vehicle_chasis_no.": "DSVBMC04941",
        "vehicle_make": "",
        "vehicle_color": "Red",
        "vehicle_model": "",
        "stolen_from": "8 satyen Roy Road Kol 34",
        "stolen_date": "10/03/2012",
        "Select_Vehicle": "",
        "Select_Status": "M",
        "Trace_Address": "",
        "Date_Of_Trace": "",
        "Presently_At": "",
        "Display": ""
    },
    {
        "state": "WEST BENGAL",
        "district": "",
        "police_station": "",
        "fir_number": "",
        "fir_date": "",
        "case_no": "Park St PS/74/12",
        "under_section": "379 IPC",
        "vehicle_registration_no": "WB38Y5865",
        "vehicle_type": "Samurai",
        "status": "Stolen",
        "control_room_no.": "",
        "complainant": "",
        "complainant_address": "",
        "vehicle_engine_no.": "DJGBSC28121",
        "vehicle_chasis_no.": "MD2DHDJZZSCJ12461",
        "vehicle_make": "Suzuki",
        "vehicle_color": "Blue",
        "vehicle_model": "Samurai",
        "stolen_from": "43 Ripon St Kol 16",
        "stolen_date": "10/03/2012",
        "Select_Vehicle": "",
        "Select_Status": "M",
        "Trace_Address": "",
        "Date_Of_Trace": "",
        "Presently_At": "",
        "Display": ""
    },
    {
        "state": "WEST BENGAL",
        "district": "",
        "police_station": "",
        "fir_number": "",
        "fir_date": "",
        "case_no": "Watgunge PS/58/12",
        "under_section": "379 IPC",
        "vehicle_registration_no": "WB221923",
        "vehicle_type": "Passion",
        "status": "Stolen",
        "control_room_no.": "",
        "complainant": "",
        "complainant_address": "",
        "vehicle_engine_no.": "HA10EDAGK53685",
        "vehicle_chasis_no.": "MBLKA10AHAGK51853",
        "vehicle_make": "Hero Honda",
        "vehicle_color": "Black",
        "vehicle_model": "Passion",
        "stolen_from": "120 C G R Road Kol 23",
        "stolen_date": "10/03/2012",
        "Select_Vehicle": "",
        "Select_Status": "M",
        "Trace_Address": "",
        "Date_Of_Trace": "",
        "Presently_At": "",
        "Display": ""
    },
    {
        "state": "WEST BENGAL",
        "district": "",
        "police_station": "",
        "fir_number": "",
        "fir_date": "",
        "case_no": "Sinthi PS/42/12",
        "under_section": "379 IPC",
        "vehicle_registration_no": "WB01X7440",
        "vehicle_type": "",
        "status": "Stolen",
        "control_room_no.": "",
        "complainant": "",
        "complainant_address": "",
        "vehicle_engine_no.": "DSGBME54832",
        "vehicle_chasis_no.": "DSVBME54881",
        "vehicle_make": "",
        "vehicle_color": "Red",
        "vehicle_model": "",
        "stolen_from": "141/A/2C South Sinthi Road Kol 50",
        "stolen_date": "09/03/2012",
        "Select_Vehicle": "",
        "Select_Status": "M",
        "Trace_Address": "",
        "Date_Of_Trace": "",
        "Presently_At": "",
        "Display": ""
    },
    {
        "state": "WEST BENGAL",
        "district": "",
        "police_station": "",
        "fir_number": "",
        "fir_date": "",
        "case_no": "Jorasanko PS/159/12",
        "under_section": "380 IPC",
        "vehicle_registration_no": "WB07E1964",
        "vehicle_type": "Samurai",
        "status": "Stolen",
        "control_room_no.": "",
        "complainant": "",
        "complainant_address": "",
        "vehicle_engine_no.": "DHGBTE57578",
        "vehicle_chasis_no.": "MD2DHDHZZTCE70414",
        "vehicle_make": "Suzuki",
        "vehicle_color": "Blue",
        "vehicle_model": "Samurai",
        "stolen_from": "35 zakaria St Kol 73",
        "stolen_date": "08/03/2012",
        "Select_Vehicle": "",
        "Select_Status": "M",
        "Trace_Address": "",
        "Date_Of_Trace": "",
        "Presently_At": "",
        "Display": ""
    },
    {
        "state": "WEST BENGAL",
        "district": "",
        "police_station": "",
        "fir_number": "",
        "fir_date": "",
        "case_no": "Entally PS/73/12",
        "under_section": "379 IPC",
        "vehicle_registration_no": "WB071639",
        "vehicle_type": "",
        "status": "Stolen",
        "control_room_no.": "",
        "complainant": "",
        "complainant_address": "",
        "vehicle_engine_no.": "DSGBNM22394",
        "vehicle_chasis_no.": "MD2DSDSZZNCM34650",
        "vehicle_make": "",
        "vehicle_color": "Red",
        "vehicle_model": "",
        "stolen_from": "150 Convent Road Kol 14",
        "stolen_date": "07/03/2012",
        "Select_Vehicle": "",
        "Select_Status": "M",
        "Trace_Address": "",
        "Date_Of_Trace": "",
        "Presently_At": "",
        "Display": ""
    },
    {
        "state": "WEST BENGAL",
        "district": "",
        "police_station": "",
        "fir_number": "",
        "fir_date": "",
        "case_no": "Entally PS/71/12",
        "under_section": "379 IPC",
        "vehicle_registration_no": "WB07C5439",
        "vehicle_type": "Samurai",
        "status": "Stolen",
        "control_room_no.": "",
        "complainant": "",
        "complainant_address": "",
        "vehicle_engine_no.": "DHGBSF56778",
        "vehicle_chasis_no.": "MD2DHDHZZSCF62365",
        "vehicle_make": "Suzuki",
        "vehicle_color": "Black",
        "vehicle_model": "Samurai",
        "stolen_from": "19/C Sir Syed Ahmed Road Kol 14",
        "stolen_date": "07/03/2012",
        "Select_Vehicle": "",
        "Select_Status": "M",
        "Trace_Address": "",
        "Date_Of_Trace": "",
        "Presently_At": "",
        "Display": ""
    },
    {
        "state": "WEST BENGAL",
        "district": "",
        "police_station": "",
        "fir_number": "",
        "fir_date": "",
        "case_no": "TIljala PS /83/12",
        "under_section": "379 IPC",
        "vehicle_registration_no": "WB01S6575",
        "vehicle_type": "",
        "status": "Stolen",
        "control_room_no.": "",
        "complainant": "",
        "complainant_address": "",
        "vehicle_engine_no.": "DFMBJB39138",
        "vehicle_chasis_no.": "DFFBJB72093",
        "vehicle_make": "",
        "vehicle_color": "Green",
        "vehicle_model": "",
        "stolen_from": "21/1 Kusthia Road Kol 39",
        "stolen_date": "07/03/2012",
        "Select_Vehicle": "",
        "Select_Status": "M",
        "Trace_Address": "",
        "Date_Of_Trace": "",
        "Presently_At": "",
        "Display": ""
    }
]